{"cameraMode":{"drawMode":0,"name":"Shaded","section":"Shading Mode"},"sceneLighting":true,"audioPlay":false,"sceneViewState":{"m_AlwaysRefresh":false,"showFog":true,"showSkybox":true,"showFlares":true,"showImageEffects":true,"showParticleSystems":true,"showVisualEffectGraphs":true,"m_FxEnabled":true},"in2DMode":false,"pivot":{"x":219.3092803955078,"y":5.557677745819092,"z":275.74322509765627},"rotation":{"x":0.05553596839308739,"y":-0.9443470239639282,"z":0.22092360258102418,"w":0.23740456998348237},"size":4.268869400024414,"orthographic":false}